simpleworker/__init__.py
simpleworker/admin.py
simpleworker/apps.py
simpleworker/models.py
simpleworker/scheduler.py
simpleworker/simple_task.py
simpleworker/simple_worker.py
simpleworker/tasks.py
simpleworker/urls.py
simpleworker/views.py
simpleworker/management/__init__.py
simpleworker/management/commands/__init__.py
simpleworker/management/commands/run_cron.py
simpleworker/management/commands/run_simple_worker.py
simpleworker/migrations/0001_initial.py
simpleworker/migrations/__init__.py
simpleworker/templates/__init__.py
simpleworker/templates/worker_status.html
django_simple_worker-0.5.28.dist-info/METADATA
django_simple_worker-0.5.28.dist-info/WHEEL
django_simple_worker-0.5.28.dist-info/top_level.txt
django_simple_worker-0.5.28.dist-info/RECORD
