Metadata-Version: 2.1
Name: django-simple-worker
Version: 0.5.28
Summary: Django Simple Worker
Home-page: https://www.idea-loop.com/
Author: idealoop
Author-email: noreply@idea-loop.com
License: MIT
Requires-Dist: django
Requires-Dist: apscheduler
Requires-Dist: sentry-sdk
